Workbook
Name taper_rate: 'DCF Model'!$C$17
Name Tax_rate: 'DCF Model'!$C$21

Sheet FSA
A1: 99 SpeedMart Financial Statement Analysis
B2: 2025 | C2: 2024 | D2: 2023 | E2: 2022 | F2: 2021
A3: P/L Statement | E3: in MYR (Millions)
A4: Sales/Revenue | B4: 11433 | C4: 9982 | D4: 9214 | E4: 8075 | F4: 7837
A5: Cost of Goods Sold (COGS) incl. D&A | B5: 10412 | C5: 9124 | D5: 8407 | E5: 7543 | F5: 7270
A6: Gross Income | B6: 1022 | C6: 858 | D6: 807 | E6: 532 | F6: 566
A7: SG&A Expense (include D&A) | B7: 1154 | C7: 999 | D7: 912 | E7: 762 | F7: 658
A8: EBIT | B8: -132 | C8: -142 | D8: -105 | E8: -230 | F8: -92
A9: Non Operating Income/Expense | B9: 993 | C9: 844 | D9: 687 | E9: 762 | F9: 703
A10: Interest Expense | B10: 48 | C10: 45 | D10: 44 | E10: 52 | F10: 53
A11: Pretax Income | B11: 814 | C11: 659 | D11: 538 | E11: 484 | F11: 562
A12: Income Tax | B12: 199 | C12: 168 | D12: 138 | E12: 157 | F12: 143
A13: Net Income | B13: 614 | C13: 490 | D13: 400 | E13: 327 | F13: 419
A15: Balance Sheet
A16: Assets
A17: Cash & Short Term Investments | B17: 898 | C17: 698 | D17: 138 | E17: 85 | F17: 350
A18: Total Accounts Receivable | B18: 45 | C18: 20 | D18: 44 | E18: 29 | F18: 18
A19: Inventories | B19: 1450 | C19: 1339 | D19: 1174 | E19: 1093 | F19: 803
A20: Other Current Assets | B20: 60 | C20: 49 | D20: 40 | E20: 36 | F20: 43
A21: Total Current Assets | B21: 2452 | C21: 2106 | D21: 1396 | E21: 1243 | F21: 1215
A22: Net Property, Plant & Equipment | B22: 1615 | C22: 1442 | D22: 1254 | E22: 1122 | F22: 1131
A23: Intangible Assets | B23: 0 | C23: 0 | D23: 0 | E23: 0 | F23: 0
A24: Total Assets | B24: 4076 | C24: 3761 | D24: 2839 | E24: 2380 | F24: 2358
A26: Liabilities
A27: ST Debt & Current Portion LT Debt | B27: 196 | C27: 176 | D27: 160 | E27: 141 | F27: 126
A28: Accounts Payable | B28: 1120 | C28: 936 | D28: 982 | E28: 805 | F28: 640
A29: Income Tax Payable | B29: 21 | C29: 25 | D29: 28 | E29: 29 | F29: 30
A30: Other Current Liabilities | B30: 81 | C30: 74 | D30: 222 | E30: 70 | F30: 66
A31: Total Current Liabilities | B31: 1419 | C31: 1212 | D31: 1391 | E31: 1045 | F31: 862
A32: Long-Term Debt | B32: 778 | C32: 712 | D32: 680 | E32: 656 | F32: 716
A33: Other Long-Term Liabilities (Provisions/Deferred Taxes) | B33: 56 | C33: 46 | D33: 37 | E33: 32 | F33: 31
A34: Total Liabilities | B34: 2261 | C34: 2182 | D34: 2298 | E34: 1749 | F34: 1621
A36: Shareholders' Equity
A37: Common Equity (Total) | B37: 1815 | C37: 1579 | D37: 542 | E37: 632 | F37: 737
A38: Liabilities & Shareholders' Equity | B38: 4076 | C38: 3761 | D38: 2839 | E38: 2380 | F38: 2358
A41: Horizontol Analysis
A42: P/L Statement | E42: in MYR (Millions)
A43: Sales/Revenue | B43: =B4/B$4 -> 1 | C43: =C4/C$4 -> 1 | D43: =D4/D$4 -> 1 | E43: =E4/E$4 -> 1 | F43: =F4/F$4 -> 1
A44: Cost of Goods Sold (COGS) incl. D&A | B44: =B5/B$4 -> 0.9106971 | C44: =C5/C$4 -> 0.91404528 | D44: =D5/D$4 -> 0.91241589 | E44: =E5/E$4 -> 0.93411765 | F44: =F5/F$4 -> 0.92765089
A45: Gross Income | B45: =B6/B$4 -> 0.089390361 | C45: =C6/C$4 -> 0.085954718 | D45: =D6/D$4 -> 0.087584111 | E45: =E6/E$4 -> 0.065882353 | F45: =F6/F$4 -> 0.072221513
A46: SG&A Expense (include D&A) | B46: =B7/B$4 -> 0.10093589 | C46: =C7/C$4 -> 0.10008014 | D46: =D7/D$4 -> 0.098979813 | E46: =E7/E$4 -> 0.094365325 | F46: =F7/F$4 -> 0.083960699
A47: EBIT | B47: =B8/B$4 -> -0.011545526 | C47: =C8/C$4 -> -0.014225606 | D47: =D8/D$4 -> -0.011395702 | E47: =E8/E$4 -> -0.028482972 | F47: =F8/F$4 -> -0.011739186
A48: Non Operating Income/Expense | B48: =B9/B$4 -> 0.086853844 | C48: =C9/C$4 -> 0.084552194 | D48: =D9/D$4 -> 0.074560451 | E48: =E9/E$4 -> 0.094365325 | F48: =F9/F$4 -> 0.089702692
A49: Interest Expense | B49: =B10/B$4 -> 0.0041983731 | C49: =C10/C$4 -> 0.0045081146 | D49: =D10/D$4 -> 0.0047753419 | E49: =E10/E$4 -> 0.0064396285 | F49: =F10/F$4 -> 0.0067627919
A50: Pretax Income | B50: =B11/B$4 -> 0.071197411 | C50: =C11/C$4 -> 0.066018834 | D50: =D11/D$4 -> 0.058389407 | E50: =E11/E$4 -> 0.05993808 | F50: =F11/F$4 -> 0.071711114
A51: Income Tax | B51: =B12/B$4 -> 0.017405755 | C51: =C12/C$4 -> 0.016830295 | D51: =D12/D$4 -> 0.014977209 | E51: =E12/E$4 -> 0.019442724 | F51: =F12/F$4 -> 0.018246778
A52: Net Income | B52: =B13/B$4 -> 0.05370419 | C52: =C13/C$4 -> 0.049088359 | D52: =D13/D$4 -> 0.043412199 | E52: =E13/E$4 -> 0.040495356 | F52: =F13/F$4 -> 0.053464336
A54: Balance Sheet
A55: Assets
A56: Cash & Short Term Investments | B56: =IF(B17/B$24=0,"",B17/B$24) -> 0.22031403 | C56: =IF(C17/C$24=0,"",C17/C$24) -> 0.18558894 | D56: =IF(D17/D$24=0,"",D17/D$24) -> 0.048608665 | E56: =IF(E17/E$24=0,"",E17/E$24) -> 0.035714286 | F56: =IF(F17/F$24=0,"",F17/F$24) -> 0.14843087
A57: Total Accounts Receivable | B57: =IF(B18/B$24=0,"",B18/B$24) -> 0.011040236 | C57: =IF(C18/C$24=0,"",C18/C$24) -> 0.0053177346 | D57: =IF(D18/D$24=0,"",D18/D$24) -> 0.015498415 | E57: =IF(E18/E$24=0,"",E18/E$24) -> 0.012184874 | F57: =IF(F18/F$24=0,"",F18/F$24) -> 0.0076335878
A58: Inventories | B58: =IF(B19/B$24=0,"",B19/B$24) -> 0.35574092 | C58: =IF(C19/C$24=0,"",C19/C$24) -> 0.35602233 | D58: =IF(D19/D$24=0,"",D19/D$24) -> 0.41352589 | E58: =IF(E19/E$24=0,"",E19/E$24) -> 0.4592437 | F58: =IF(F19/F$24=0,"",F19/F$24) -> 0.34054283
A59: Other Current Assets | B59: =IF(B20/B$24=0,"",B20/B$24) -> 0.014720314 | C59: =IF(C20/C$24=0,"",C20/C$24) -> 0.01302845 | D59: =IF(D20/D$24=0,"",D20/D$24) -> 0.014089468 | E59: =IF(E20/E$24=0,"",E20/E$24) -> 0.01512605 | F59: =IF(F20/F$24=0,"",F20/F$24) -> 0.018235793
A60: Total Current Assets | B60: =IF(B21/B$24=0,"",B21/B$24) -> 0.60157017 | C60: =IF(C21/C$24=0,"",C21/C$24) -> 0.55995746 | D60: =IF(D21/D$24=0,"",D21/D$24) -> 0.49172244 | E60: =IF(E21/E$24=0,"",E21/E$24) -> 0.52226891 | F60: =IF(F21/F$24=0,"",F21/F$24) -> 0.51526718
A61: Net Property, Plant & Equipment | B61: =IF(B22/B$24=0,"",B22/B$24) -> 0.39622179 | C61: =IF(C22/C$24=0,"",C22/C$24) -> 0.38340867 | D61: =IF(D22/D$24=0,"",D22/D$24) -> 0.44170483 | E61: =IF(E22/E$24=0,"",E22/E$24) -> 0.47142857 | F61: =IF(F22/F$24=0,"",F22/F$24) -> 0.47964377
A62: Intangible Assets | B62: =IF(B23/B$24=0,"",B23/B$24) | C62: =IF(C23/C$24=0,"",C23/C$24) | D62: =IF(D23/D$24=0,"",D23/D$24) | E62: =IF(E23/E$24=0,"",E23/E$24) | F62: =IF(F23/F$24=0,"",F23/F$24)
A63: Total Assets | B63: =IF(B24/B$24=0,"",B24/B$24) -> 1 | C63: =IF(C24/C$24=0,"",C24/C$24) -> 1 | D63: =IF(D24/D$24=0,"",D24/D$24) -> 1 | E63: =IF(E24/E$24=0,"",E24/E$24) -> 1 | F63: =IF(F24/F$24=0,"",F24/F$24) -> 1
B64: =IF(B25/B$24=0,"",B25/B$24) | C64: =IF(C25/C$24=0,"",C25/C$24) | D64: =IF(D25/D$24=0,"",D25/D$24) | E64: =IF(E25/E$24=0,"",E25/E$24) | F64: =IF(F25/F$24=0,"",F25/F$24)
A65: Liabilities | B65: =IF(B26/B$24=0,"",B26/B$24) | C65: =IF(C26/C$24=0,"",C26/C$24) | D65: =IF(D26/D$24=0,"",D26/D$24) | E65: =IF(E26/E$24=0,"",E26/E$24) | F65: =IF(F26/F$24=0,"",F26/F$24)
A66: ST Debt & Current Portion LT Debt | B66: =IF(B27/B$24=0,"",B27/B$24) -> 0.048086359 | C66: =IF(C27/C$24=0,"",C27/C$24) -> 0.046796065 | D66: =IF(D27/D$24=0,"",D27/D$24) -> 0.056357872 | E66: =IF(E27/E$24=0,"",E27/E$24) -> 0.059243697 | F66: =IF(F27/F$24=0,"",F27/F$24) -> 0.053435115
A67: Accounts Payable | B67: =IF(B28/B$24=0,"",B28/B$24) -> 0.2747792 | C67: =IF(C28/C$24=0,"",C28/C$24) -> 0.24886998 | D67: =IF(D28/D$24=0,"",D28/D$24) -> 0.34589644 | E67: =IF(E28/E$24=0,"",E28/E$24) -> 0.33823529 | F67: =IF(F28/F$24=0,"",F28/F$24) -> 0.27141645
A68: Income Tax Payable | B68: =IF(B29/B$24=0,"",B29/B$24) -> 0.0051521099 | C68: =IF(C29/C$24=0,"",C29/C$24) -> 0.0066471683 | D68: =IF(D29/D$24=0,"",D29/D$24) -> 0.0098626277 | E68: =IF(E29/E$24=0,"",E29/E$24) -> 0.012184874 | F68: =IF(F29/F$24=0,"",F29/F$24) -> 0.012722646
A69: Other Current Liabilities | B69: =IF(B30/B$24=0,"",B30/B$24) -> 0.019872424 | C69: =IF(C30/C$24=0,"",C30/C$24) -> 0.019675618 | D69: =IF(D30/D$24=0,"",D30/D$24) -> 0.078196548 | E69: =IF(E30/E$24=0,"",E30/E$24) -> 0.029411765 | F69: =IF(F30/F$24=0,"",F30/F$24) -> 0.027989822
A70: Total Current Liabilities | B70: =IF(B31/B$24=0,"",B31/B$24) -> 0.34813543 | C70: =IF(C31/C$24=0,"",C31/C$24) -> 0.32225472 | D70: =IF(D31/D$24=0,"",D31/D$24) -> 0.48996125 | E70: =IF(E31/E$24=0,"",E31/E$24) -> 0.43907563 | F70: =IF(F31/F$24=0,"",F31/F$24) -> 0.36556404
A71: Long-Term Debt | B71: =IF(B32/B$24=0,"",B32/B$24) -> 0.19087341 | C71: =IF(C32/C$24=0,"",C32/C$24) -> 0.18931135 | D71: =IF(D32/D$24=0,"",D32/D$24) -> 0.23952096 | E71: =IF(E32/E$24=0,"",E32/E$24) -> 0.27563025 | F71: =IF(F32/F$24=0,"",F32/F$24) -> 0.30364716
A72: Other Long-Term Liabilities (Provisions/Deferred Taxes) | B72: =IF(B33/B$24=0,"",B33/B$24) -> 0.01373896 | C72: =IF(C33/C$24=0,"",C33/C$24) -> 0.01223079 | D72: =IF(D33/D$24=0,"",D33/D$24) -> 0.013032758 | E72: =IF(E33/E$24=0,"",E33/E$24) -> 0.013445378 | F72: =IF(F33/F$24=0,"",F33/F$24) -> 0.013146735
A73: Total Liabilities | B73: =IF(B34/B$24=0,"",B34/B$24) -> 0.5547105 | C73: =IF(C34/C$24=0,"",C34/C$24) -> 0.58016485 | D73: =IF(D34/D$24=0,"",D34/D$24) -> 0.80943994 | E73: =IF(E34/E$24=0,"",E34/E$24) -> 0.73487395 | F73: =IF(F34/F$24=0,"",F34/F$24) -> 0.68744699
B74: =IF(B35/B$24=0,"",B35/B$24) | C74: =IF(C35/C$24=0,"",C35/C$24) | D74: =IF(D35/D$24=0,"",D35/D$24) | E74: =IF(E35/E$24=0,"",E35/E$24) | F74: =IF(F35/F$24=0,"",F35/F$24)
A75: Shareholders' Equity | B75: =IF(B36/B$24=0,"",B36/B$24) | C75: =IF(C36/C$24=0,"",C36/C$24) | D75: =IF(D36/D$24=0,"",D36/D$24) | E75: =IF(E36/E$24=0,"",E36/E$24) | F75: =IF(F36/F$24=0,"",F36/F$24)
A76: Common Equity (Total) | B76: =IF(B37/B$24=0,"",B37/B$24) -> 0.4452895 | C76: =IF(C37/C$24=0,"",C37/C$24) -> 0.41983515 | D76: =IF(D37/D$24=0,"",D37/D$24) -> 0.19091229 | E76: =IF(E37/E$24=0,"",E37/E$24) -> 0.26554622 | F76: =IF(F37/F$24=0,"",F37/F$24) -> 0.31255301
A77: Liabilities & Shareholders' Equity | B77: =IF(B38/B$24=0,"",B38/B$24) -> 1 | C77: =IF(C38/C$24=0,"",C38/C$24) -> 1 | D77: =IF(D38/D$24=0,"",D38/D$24) -> 1 | E77: =IF(E38/E$24=0,"",E38/E$24) -> 1 | F77: =IF(F38/F$24=0,"",F38/F$24) -> 1
A80: Vertical Analysis
A81: P/L Statement | E81: in MYR (Millions)
A82: Sales/Revenue | B82: =(B4-C4)/C4 -> 0.14536165 | C82: =(C4-D4)/D4 -> 0.083351422 | D82: =(D4-E4)/E4 -> 0.14105263 | E82: =(E4-F4)/F4 -> 0.030368764
A83: Cost of Goods Sold (COGS) incl. D&A | B83: =(B5-C5)/C5 -> 0.14116616 | C83: =(C5-D5)/D5 -> 0.085286071 | D83: =(D5-E5)/E5 -> 0.11454329 | E83: =(E5-F5)/F5 -> 0.037551582
A84: Gross Income | B84: =(B6-C6)/C6 -> 0.19114219 | C84: =(C6-D6)/D6 -> 0.063197026 | D84: =(D6-E6)/E6 -> 0.51691729 | E84: =(E6-F6)/F6 -> -0.060070671
A85: SG&A Expense (include D&A) | B85: =(B7-C7)/C7 -> 0.15515516 | C85: =(C7-D7)/D7 -> 0.095394737 | D85: =(D7-E7)/E7 -> 0.19685039 | E85: =(E7-F7)/F7 -> 0.15805471
A86: EBIT | B86: =(B8-C8)/C8 -> -0.070422535 | C86: =(C8-D8)/D8 -> 0.35238095 | D86: =(D8-E8)/E8 -> -0.54347826 | E86: =(E8-F8)/F8 -> 1.5
A87: Non Operating Income/Expense | B87: =(B9-C9)/C9 -> 0.17654028 | C87: =(C9-D9)/D9 -> 0.22852984 | D87: =(D9-E9)/E9 -> -0.098425197 | E87: =(E9-F9)/F9 -> 0.083926031
A88: Interest Expense | B88: =(B10-C10)/C10 -> 0.066666667 | C88: =(C10-D10)/D10 -> 0.022727273 | D88: =(D10-E10)/E10 -> -0.15384615 | E88: =(E10-F10)/F10 -> -0.018867925
A89: Pretax Income | B89: =(B11-C11)/C11 -> 0.23520486 | C89: =(C11-D11)/D11 -> 0.22490706 | D89: =(D11-E11)/E11 -> 0.11157025 | E89: =(E11-F11)/F11 -> -0.13879004
A90: Income Tax | B90: =(B12-C12)/C12 -> 0.18452381 | C90: =(C12-D12)/D12 -> 0.2173913 | D90: =(D12-E12)/E12 -> -0.12101911 | E90: =(E12-F12)/F12 -> 0.097902098
A91: Net Income | B91: =(B13-C13)/C13 -> 0.25306122 | C91: =(C13-D13)/D13 -> 0.225 | D91: =(D13-E13)/E13 -> 0.22324159 | E91: =(E13-F13)/F13 -> -0.21957041
A93: Balance Sheet
A94: Assets
A95: Cash & Short Term Investments | B95: =(B17-C17)/C17 -> 0.28653295 | C95: =(C17-D17)/D17 -> 4.057971 | D95: =(D17-E17)/E17 -> 0.62352941 | E95: =(E17-F17)/F17 -> -0.75714286
A96: Total Accounts Receivable | B96: =(B18-C18)/C18 -> 1.25 | C96: =(C18-D18)/D18 -> -0.54545455 | D96: =(D18-E18)/E18 -> 0.51724138 | E96: =(E18-F18)/F18 -> 0.61111111
A97: Inventories | B97: =(B19-C19)/C19 -> 0.082897685 | C97: =(C19-D19)/D19 -> 0.14054514 | D97: =(D19-E19)/E19 -> 0.07410796 | E97: =(E19-F19)/F19 -> 0.3611457
A98: Other Current Assets | B98: =(B20-C20)/C20 -> 0.2244898 | C98: =(C20-D20)/D20 -> 0.225 | D98: =(D20-E20)/E20 -> 0.11111111 | E98: =(E20-F20)/F20 -> -0.1627907
A99: Total Current Assets | B99: =(B21-C21)/C21 -> 0.1642925 | C99: =(C21-D21)/D21 -> 0.50859599 | D99: =(D21-E21)/E21 -> 0.1230893 | E99: =(E21-F21)/F21 -> 0.023045267
A100: Net Property, Plant & Equipment | B100: =(B22-C22)/C22 -> 0.11997226 | C100: =(C22-D22)/D22 -> 0.14992026 | D100: =(D22-E22)/E22 -> 0.11764706 | E100: =(E22-F22)/F22 -> -0.0079575597
A101: Intangible Assets
A102: Total Assets | B102: =(B24-C24)/C24 -> 0.083754321 | C102: =(C24-D24)/D24 -> 0.32476224 | D102: =(D24-E24)/E24 -> 0.19285714 | E102: =(E24-F24)/F24 -> 0.0093299406
A104: Liabilities
A105: ST Debt & Current Portion LT Debt | B105: =(B27-C27)/C27 -> 0.11363636 | C105: =(C27-D27)/D27 -> 0.1 | D105: =(D27-E27)/E27 -> 0.13475177 | E105: =(E27-F27)/F27 -> 0.11904762
A106: Accounts Payable | B106: =(B28-C28)/C28 -> 0.1965812 | C106: =(C28-D28)/D28 -> -0.046843177 | D106: =(D28-E28)/E28 -> 0.21987578 | E106: =(E28-F28)/F28 -> 0.2578125
A107: Income Tax Payable | B107: =(B29-C29)/C29 -> -0.16 | C107: =(C29-D29)/D29 -> -0.10714286 | D107: =(D29-E29)/E29 -> -0.034482759 | E107: =(E29-F29)/F29 -> -0.033333333
A108: Other Current Liabilities | B108: =(B30-C30)/C30 -> 0.094594595 | C108: =(C30-D30)/D30 -> -0.66666667 | D108: =(D30-E30)/E30 -> 2.1714286 | E108: =(E30-F30)/F30 -> 0.060606061
A109: Total Current Liabilities | B109: =(B31-C31)/C31 -> 0.17079208 | C109: =(C31-D31)/D31 -> -0.1286844 | D109: =(D31-E31)/E31 -> 0.33110048 | E109: =(E31-F31)/F31 -> 0.21229698
A110: Long-Term Debt | B110: =(B32-C32)/C32 -> 0.092696629 | C110: =(C32-D32)/D32 -> 0.047058824 | D110: =(D32-E32)/E32 -> 0.036585366 | E110: =(E32-F32)/F32 -> -0.083798883
...

Sheet DCF Model
B1: Discounted Cash Flow (DCF)
B4: Company Overview
B6: 99 Speedmart is a retail chain, specifically a mini-supermarket chain focusing on groceries and daily neccessities
B8: Total Store Count: 3,000+ outlets across Malaysia
B11: Key Assumptions & Methodology
B13: Parameter | C13: Value | D13: Rationale
B14: Valuation Date
B15: Projection Period
B16: Revenue Growth% | C16: 0.09 | D16: Top-down industry trends (retail sector growing at 7.0%, + market leader premium)
B17: Annual Growth Tapering | C17: 0.01
B18: Terminal Growth Rate | C18: 0.02 | D18: Conservative long-term growth
B19: Risk-Free Rate (Rf) | C19: 0.035 | D19: Malaysian 10-Year Government Bond Yield
B20: Equity Risk Premium (ERP) | C20: 0.0578 | D20: Expected return over risk-free rate for invetors
B21: Tax Rate | C21: 0.24 | D21: Effective tax rate based on historical data
B24: Financial Performance (RM Million)
B26: Income Statement
B27: Particulars | C27: 2025 | D27: 2024 | E27: 2023 | F27: 2022 | G27: 2021
B28: Sales | C28: =Data!B4 -> 11433 | D28: =Data!C4 -> 9982 | E28: =Data!D4 -> 9214 | F28: =Data!E4 -> 8075 | G28: =Data!F4 -> 7837
B29: % growth | C29: =C28/D28-1 -> 0.14536165 | D29: =D28/E28-1 -> 0.083351422 | E29: =E28/F28-1 -> 0.14105263 | F29: =F28/G28-1 -> 0.030368764
B30: Cost of Goods Sold | C30: =Data!B7 -> 10135 | D30: =Data!C7 -> 8877 | E30: =Data!D7 -> 8185 | F30: =Data!E7 -> 7334 | G30: =Data!F7 -> 7081
B31: % of revenue | C31: =C30/C28 -> 0.88646899 | D31: =D30/D28 -> 0.88930074 | E31: =E30/E28 -> 0.88832212 | F31: =F30/F28 -> 0.90823529 | G31: =G30/G28 -> 0.90353452
B32: Gross Profit | C32: =Data!B12+Data!B8 -> 1299 | D32: =Data!C12+Data!C8 -> 1105 | E32: =Data!D12+Data!D8 -> 1030 | F32: =Data!E12+Data!E8 -> 741 | G32: =Data!F12+Data!F8 -> 756
B33: % margin | C33: =C32/C28 -> 0.11361847 | D33: =D32/D28 -> 0.11069926 | E33: =E32/E28 -> 0.11178641 | F33: =F32/F28 -> 0.091764706 | G33: =G32/G28 -> 0.096465484
B34: Operating Expenses | C34: =Data!B16 -> 1154 | D34: =Data!C16 -> 999 | E34: =Data!D16 -> 912 | F34: =Data!E16 -> 762 | G34: =Data!F16 -> 658
B35: % of revenue | C35: =C34/C28 -> 0.10093589 | D35: =D34/D28 -> 0.10008014 | E35: =E34/E28 -> 0.098979813 | F35: =F34/F28 -> 0.094365325 | G35: =G34/G28 -> 0.083960699
B36: EBITDA | C36: =C32-C34 -> 145 | D36: =D32-D34 -> 106 | E36: =E32-E34 -> 118 | F36: =F32-F34 -> -21 | G36: =G32-G34 -> 98
B37: % margin | C37: =C36/C28 -> 0.012682585 | D37: =D36/D28 -> 0.010619114 | E37: =E36/E28 -> 0.012806599 | F37: =F36/F28 -> -0.0026006192 | G37: =G36/G28 -> 0.012504785
B38: Depreciation | C38: =Data!B9 -> 277 | D38: =Data!C9 -> 247 | E38: =Data!D9 -> 223 | F38: =Data!E9 -> 209 | G38: =Data!F9 -> 190
B39: % of net sales | C39: =C38/C28 -> 0.024228112 | D39: =D38/D28 -> 0.02474454 | E39: =E38/E28 -> 0.024202301 | F39: =F38/F28 -> 0.025882353 | G39: =G38/G28 -> 0.024243971
B40: EBIT | C40: =C36-C38+Data!B21 -> -132 | D40: =D36-D38+Data!C21 -> -142 | E40: =E36-E38+Data!D21 -> -105 | F40: =F36-F38+Data!E21 -> -230 | G40: =G36-G38+Data!F21 -> -92
B41: % margin | C41: =C40/C28 -> -0.011545526 | D41: =D40/D28 -> -0.014225606 | E41: =E40/E28 -> -0.011395702 | F41: =F40/F28 -> -0.028482972 | G41: =G40/G28 -> -0.011739186
B42: Other Income | C42: =Data!B23 -> 993 | D42: =Data!C23 -> 844 | E42: =Data!D23 -> 687 | F42: =Data!E23 -> 762 | G42: =Data!F23 -> 703
B43: Interest | C43: =Data!B25 -> 48 | D43: =Data!C25 -> 45 | E43: =Data!D25 -> 44 | F43: =Data!E25 -> 52 | G43: =Data!F25 -> 53
B44: % of debt | C44: =C43/Data!B100 -> 0.24489796 | D44: =D43/Data!C100 -> 0.25568182 | E44: =E43/Data!D100 -> 0.275 | F44: =F43/Data!E100 -> 0.36879433 | G44: =G43/Data!F100 -> 0.42063492
B45: Profit before tax | C45: =Data!B29 -> 814 | D45: =Data!C29 -> 659 | E45: =Data!D29 -> 538 | F45: =Data!E29 -> 484 | G45: =Data!F29 -> 562
B46: % of revenue | C46: =C45/C28 -> 0.071197411 | D46: =D45/D28 -> 0.066018834 | E46: =E45/E28 -> 0.058389407 | F46: =F45/F28 -> 0.05993808 | G46: =G45/G28 -> 0.071711114
B47: Tax | C47: =Data!B33 -> 199 | D47: =Data!C33 -> 168 | E47: =Data!D33 -> 138 | F47: =Data!E33 -> 157 | G47: =Data!F33 -> 143
B48: % of PBT | C48: =C47/C45 -> 0.24447174 | D48: =D47/D45 -> 0.25493171 | E48: =E47/E45 -> 0.25650558 | F48: =F47/F45 -> 0.32438017 | G48: =G47/G45 -> 0.2544484
B49: Net profit | C49: =Data!B38 -> 614 | D49: =Data!C38 -> 490 | E49: =Data!D38 -> 400 | F49: =Data!E38 -> 327 | G49: =Data!F38 -> 419
B50: % of revenue | C50: =C49/C28 -> 0.05370419 | D50: =D49/D28 -> 0.049088359 | E50: =E49/E28 -> 0.043412199 | F50: =F49/F28 -> 0.040495356 | G50: =G49/G28 -> 0.053464336
B52: Balance Sheet
B53: Particulars | C53: 2025 | D53: 2024 | E53: 2023 | F53: 2022 | G53: 2021
B54: Assets
B55: Cash & Short Term Investments | C55: 898 | D55: 698 | E55: 138 | F55: 85 | G55: 350
B56: Total Accounts Receivable | C56: 45 | D56: 20 | E56: 44 | F56: 29 | G56: 18
B57: Inventories | C57: 1450 | D57: 1339 | E57: 1174 | F57: 1093 | G57: 803
B58: Other Current Assets | C58: 60 | D58: 49 | E58: 40 | F58: 36 | G58: 43
B59: Total Current Assets | C59: 2452 | D59: 2106 | E59: 1396 | F59: 1243 | G59: 1215
B60: Net Property, Plant & Equipment | C60: 1615 | D60: 1442 | E60: 1254 | F60: 1122 | G60: 1131
B61: Intangible Assets | C61: 0 | D61: 0 | E61: 0 | F61: 0 | G61: 0
B62: Total Assets | C62: 4076 | D62: 3761 | E62: 2839 | F62: 2380 | G62: 2358
B64: Liabilities
B65: ST Debt & Current Portion LT Debt | C65: 196 | D65: 176 | E65: 160 | F65: 141 | G65: 126
B66: Accounts Payable | C66: 1120 | D66: 936 | E66: 982 | F66: 805 | G66: 640
B67: Income Tax Payable | C67: 21 | D67: 25 | E67: 28 | F67: 29 | G67: 30
B68: Other Current Liabilities | C68: 81 | D68: 74 | E68: 222 | F68: 70 | G68: 66
B69: Total Current Liabilities | C69: 1419 | D69: 1212 | E69: 1391 | F69: 1045 | G69: 862
B70: Long-Term Debt | C70: 778 | D70: 712 | E70: 680 | F70: 656 | G70: 716
B71: Other Long-Term Liabilities (Provisions/Deferred Taxes) | C71: 56 | D71: 46 | E71: 37 | F71: 32 | G71: 31
B72: Total Liabilities | C72: 2261 | D72: 2182 | E72: 2298 | F72: 1749 | G72: 1621
B74: Shareholders' Equity
B75: Common Equity (Total) | C75: 1815 | D75: 1579 | E75: 542 | F75: 632 | G75: 737
B76: Liabilities & Shareholders' Equity | C76: 4076 | D76: 3761 | E76: 2839 | F76: 2380 | G76: 2358
B79: Revenue Projection & Growth Assumption
B81: Year | C81: FY26 | D81: FY27 | E81: FY28 | F81: FY29 | G81: FY30
B82: Revenue Growth % | C82: {=CHOOSE(D84,C85:G85,C86:G86,C87:G87)} -> 0.11 | D82: 0.1 | E82: 0.09 | F82: 0.08 | G82: 0.07
B83: Revenue (in Crs.) | C83: =C28*(1+C82) -> 12690.63 | D83: =C83*(1+D82) -> 13959.693 | E83: =D83*(1+E82) -> 15216.065 | F83: =E83*(1+F82) -> 16433.351 | G83: =F83*(1+G82) -> 17583.685
B84: Chosen Scenario: | C84: Best Case | D84: =MATCH(C84,B85:B87,0) -> 2
B85: Base Case | C85: =C16 -> 0.09 | D85: =C85-taper_rate -> 0.08 | E85: =D85-taper_rate -> 0.07 | F85: =E85-taper_rate -> 0.06 | G85: =F85-taper_rate -> 0.05
B86: Best Case | C86: =C85+2% -> 0.11 | D86: =C86-taper_rate -> 0.1 | E86: =D86-taper_rate -> 0.09 | F86: =E86-taper_rate -> 0.08 | G86: =F86-taper_rate -> 0.07
B87: Worst Case | C87: =C85-2% -> 0.07 | D87: =C87-taper_rate -> 0.06 | E87: =D87-taper_rate -> 0.05 | F87: =E87-taper_rate -> 0.04 | G87: =F87-taper_rate -> 0.03
B90: Free Cash Flow Projections (RM Million)
B92: Particulars | C92: FY26 | D92: FY27 | E92: FY28 | F92: FY29 | G92: FY30
B93: Revenue | C93: =C83 -> 12690.63 | D93: =D83 -> 13959.693 | E93: =E83 -> 15216.065 | F93: =F83 -> 16433.351 | G93: =G83 -> 17583.685
B94: EBITDA Margin % | C94: =C37 -> 0.012682585 | D94: =C94 -> 0.012682585 | E94: =D94 -> 0.012682585 | F94: =E94 -> 0.012682585 | G94: =F94 -> 0.012682585
B95: EBITDA | C95: =C93*C94 -> 160.95 | D95: =D93*D94 -> 177.045 | E95: =E93*E94 -> 192.97905 | F95: =F93*F94 -> 208.41737 | G95: =G93*G94 -> 223.00659
B96: Less: Depreciation | C96: =C93*AVERAGE($C$39:$G$39) -> 312.95418 | D96: =D93*AVERAGE($C$39:$G$39) -> 344.24959 | E96: =E93*AVERAGE($C$39:$G$39) -> 375.23206 | F96: =F93*AVERAGE($C$39:$G$39) -> 405.25062 | G96: =G93*AVERAGE($C$39:$G$39) -> 433.61816
B97: EBIT | C97: =C95-C96 -> -152.00418 | D97: =D95-D96 -> -167.20459 | E97: =E95-E96 -> -182.25301 | F97: =F95-F96 -> -196.83325 | G97: =G95-G96 -> -210.61157
B98: Non-Operating Income | C98: =C42*(1+6%) -> 1052.58 | D98: =C98*(1+6%) -> 1115.7348 | E98: =D98*(1+6%) -> 1182.6789 | F98: =E98*(1+6%) -> 1253.6396 | G98: =F98*(1+6%) -> 1328.858
B99: Less: Tax | C99: =C98*Tax_rate -> 252.6192 | D99: =D98*Tax_rate -> 267.77635 | E99: =E98*Tax_rate -> 283.84293 | F99: =F98*Tax_rate -> 300.87351 | G99: =G98*Tax_rate -> 318.92592
B100: NOPAT | C100: =C98-C99 -> 799.9608 | D100: =D98-D99 -> 847.95845 | E100: =E98-E99 -> 898.83595 | F100: =F98-F99 -> 952.76611 | G100: =G98-G99 -> 1009.9321
B101: Add: Depreciation | C101: =C100+C96 -> 1112.915 | D101: =D100+D96 -> 1192.208 | E101: =E100+E96 -> 1274.068 | F101: =F100+F96 -> 1358.0167 | G101: =G100+G96 -> 1443.5502
B102: Less: Reinvestment | C102: =C100*50% -> 399.9804 | D102: =D100*50% -> 423.97922 | E102: =E100*50% -> 449.41798 | F102: =F100*50% -> 476.38306 | G102: =G100*50% -> 504.96604
B103: Free Cash Flow to Firm | C103: =C100+C101-C102 -> 1512.8954 | D103: =D100+D101-D102 -> 1616.1873 | E103: =E100+E101-E102 -> 1723.486 | F103: =F100+F101-F102 -> 1834.3998 | G103: =G100+G101-G102 -> 1948.5163
B106: WACC Calculation
B108: Target Capital Structure
B109: Proportion of Debt | C109: ='Comps '!F23 -> 0.24262501
B110: Proportion of Equity | C110: =1-C109 -> 0.75737499
B111: Current Capital Structure
B112: Market Cap | C112: ='Comps '!E7 -> 28980
B113: Total Debt | C113: ='Comps '!J7 -> 974
B114: Debt / Equity | C114: =C113/C112 -> 0.033609386
B115: Cost of Debt
B116: Pre-Tax Cost of Debt | C116: =Data!E251 -> 0.052468506
B117: Tax Rate | C117: =Tax_rate -> 0.24
B118: After-Tax Cost of Debt | C118: =C116*(1-C117) -> 0.039876064
B119: Cost of Equity
B120: Risk Free Rate | C120: =C19 -> 0.035
B121: Equity Risk Premium | C121: =C20 -> 0.0578
B122: Levered Equity Beta | C122: ='Comps '!I23*(1+C114*(1-Tax_rate)) -> 0.24553951
...

Sheet Comps 
B4: Comps Data (Million)
B6: Company | C6: Ticker | D6: Price | E6: Market Cap | F6: Sales | G6: EBITDA | H6: Net Income | I6: Beta | J6: Total Debt | K6: Cash & Cash Equivalents | L6: EV/EBITDA | M6: P/E
B7: 99 Speed Mart Retail Holdings Berhad | C7: 5326.KL | D7: 3.5 | E7: 28980 | F7: 11433 | G7: 888 | H7: 614 | I7: 1.22 | J7: 974 | K7: 897 | L7: 199.99 | M7: 43.88
B8: Eco-Shop Marketing Berhad | C8: 5296.KL | D8: 1.57 | E8: 9090 | F8: 2790 | G8: 442 | H8: 231 | I8: 0.06 | J8: 446 | K8: 248 | L8: 21.02 | M8: 39.21
B9: AEON Co. (Malaysia) Bhd. | C9: 6599.KL | D9: 1.17 | E9: 1680 | F9: 4290 | G9: 741 | H9: 113 | I9: 0.88 | J9: 2410 | K9: 354 | L9: 4.83 | M9: 14.75
B10: 7-Eleven Malaysia Holdings Bhd | C10: 5250.KL | D10: 1.99 | E10: 2120 | F10: 3180 | G10: 158 | H10: 32 | I10: -0.06 | J10: 1370 | K10: 105 | L10: 21.89 | M10: 68.75
B11: CCK Consolidated Holdings Bhd. | C11: 7035.KL | D11: 1.22 | E11: 783 | F11: 1050 | G11: 221 | H11: 67 | I11: 0.55 | J11: 80 | K11: 235 | L11: 2.93 | M11: 11.03
B14: Industry Beta
C16: Equity | D16: Total | E16: Debt/ | F16: Debt/ | G16: Tax | H16: Levered | I16: Unlevered
B17: Company Name | C17: Value | D17: Debt | E17: Equity | F17: Capital | G17: Rate % | H17: Beta | I17: Beta
B18: Eco-Shop Marketing Berhad | C18: =E8 -> 9090 | D18: =J8 -> 446 | E18: =D18/C18 -> 0.049064906 | F18: =D18/(C18+D18) -> 0.046770134 | G18: =Tax_rate -> 0.24 | H18: =I8 -> 0.06 | I18: =H18/(1+E18*(1-G18)) -> 0.057843071
B19: AEON Co. (Malaysia) Bhd. | C19: =E9 -> 1680 | D19: =J9 -> 2410 | E19: =D19/C19 -> 1.4345238 | F19: =D19/(C19+D19) -> 0.58924205 | G19: =Tax_rate -> 0.24 | H19: =I9 -> 0.88 | I19: =H19/(1+E19*(1-G19)) -> 0.42100467
B20: 7-Eleven Malaysia Holdings Bhd | C20: =E10 -> 2120 | D20: =J10 -> 1370 | E20: =D20/C20 -> 0.64622642 | F20: =D20/(C20+D20) -> 0.39255014 | G20: =Tax_rate -> 0.24 | H20: =I10 -> -0.06 | I20: =H20/(1+E20*(1-G20)) -> -0.040237884
B21: CCK Consolidated Holdings Bhd. | C21: =E11 -> 783 | D21: =J11 -> 80 | E21: =D21/C21 -> 0.10217114 | F21: =D21/(C21+D21) -> 0.092699884 | G21: =Tax_rate -> 0.24 | H21: =I11 -> 0.55 | I21: =H21/(1+E21*(1-G21)) -> 0.51036976
B22: Average | E22: =AVERAGE(E18:E21) -> 0.55799657 | F22: =AVERAGE(F18:F21) -> 0.28031555 | G22: =AVERAGE(G18:G21) -> 0.24 | H22: =AVERAGE(H18:H21) -> 0.3575 | I22: =AVERAGE(I18:I21) -> 0.2372449
B23: Median | E23: =MEDIAN(E18:E21) -> 0.37419878 | F23: =MEDIAN(F18:F21) -> 0.24262501 | G23: =MEDIAN(G18:G21) -> 0.24 | H23: =MEDIAN(H18:H21) -> 0.305 | I23: =MEDIAN(I18:I21) -> 0.23942387

Sheet Data
A2: Income Statement
A3: Fiscal year is January-December. All values MYR Millions. | B3: 2025 | C3: 2024 | D3: 2023 | E3: 2022 | F3: 2021
A4: Sales/Revenue | B4: 11433 | C4: 9982 | D4: 9214 | E4: 8075 | F4: 7837
A5: Sales Growth | B5: 0.1454 | C5: 0.0833 | D5: 0.141 | E5: 0.0304 | F5: -
A6: Cost of Goods Sold (COGS) incl. D&A | B6: 10412 | C6: 9124 | D6: 8407 | E6: 7543 | F6: 7270
A7: COGS excluding D&A | B7: 10135 | C7: 8877 | D7: 8185 | E7: 7334 | F7: 7081
A8: Depreciation & Amortization Expense | B8: 277 | C8: 247 | D8: 223 | E8: 209 | F8: 190
A9: Depreciation | B9: 277 | C9: 247 | D9: 223 | E9: 209 | F9: 190
A10: Amortization of Intangibles | B10: 0 | C10: 0 | D10: - | E10: 0 | F10: 0
A11: COGS Growth | B11: 0.1411 | C11: 0.0852 | D11: 0.1145 | E11: 0.0376 | F11: -
A12: Gross Income | B12: 1022 | C12: 858 | D12: 807 | E12: 532 | F12: 566
A13: Gross Income Growth | B13: 0.191 | C13: 0.0632 | D13: 0.517 | E13: -0.0609 | F13: -
A15: Gross Profit Margin | B15: 0.0894 | C15: - | D15: - | E15: - | F15: -
A16: SG&A Expense | B16: 1154 | C16: 999 | D16: 912 | E16: 762 | F16: 658
A17: Other SG&A | B17: 1154 | C17: 999 | D17: 912 | E17: 762 | F17: 658
A18: SGA Growth | B18: 0.1543 | C18: 0.0963 | D18: 0.197 | E18: 0.1564 | F18: -
A19: EBIT | B19: -132 | C19: -142 | D19: -105 | E19: -230 | F19: -92
A21: Unusual Expense | B21: 0 | C21: -1 | D21: 0 | E21: 0 | F21: 0
A23: Non Operating Income/Expense | B23: 993 | C23: 844 | D23: 687 | E23: 762 | F23: 703
A24: Non-Operating Interest Income | B24: - | C24: - | D24: - | E24: 3 | F24: 5
A25: Interest Expense | B25: 48 | C25: 45 | D25: 44 | E25: 52 | F25: 53
A26: Interest Expense Growth | B26: 0.0639 | C26: 0.0228 | D26: -0.1459 | E26: -0.0326 | F26: -
A28: Gross Interest Expense | B28: 48 | C28: 45 | D28: 44 | E28: 52 | F28: 53
A29: Pretax Income | B29: 814 | C29: 659 | D29: 538 | E29: 484 | F29: 562
A30: Pretax Income Growth | B30: 0.2353 | C30: 0.2237 | D30: 0.1117 | E30: -0.1383 | F30: -
A32: Pretax Margin | B32: 0.0712 | C32: - | D32: - | E32: - | F32: -
A33: Income Tax | B33: 199 | C33: 168 | D33: 138 | E33: 157 | F33: 143
A34: Income Tax - Current Domestic | B34: - | C34: 165 | D34: 139 | E34: 161 | F34: 148
A35: Income Tax - Deferred Domestic | B35: - | C35: 4 | D35: -1 | E35: -4 | F35: -5
A37: Consolidated Net Income | B37: 614 | C37: 490 | D37: 400 | E37: 327 | F37: 419
A38: Net Income | B38: 614 | C38: 490 | D38: 400 | E38: 327 | F38: 419
A39: Net Income Growth | B39: 0.2528 | C39: 0.225 | D39: 0.2252 | E39: -0.2205 | F39: -
A41: Net Margin | B41: 0.0537 | C41: - | D41: - | E41: - | F41: -
A42: Net Income After Extraordinaries | B42: 614 | C42: 490 | D42: 400 | E42: 327 | F42: 419
A43: Net Income Available to Common | B43: 614 | C43: 490 | D43: 400 | E43: 327 | F43: 419
A44: EPS (Basic) | B44: 0.07 | C44: 0.06 | D44: 0.05 | E44: 0.04 | F44: 0.05
A45: EPS (Basic) Growth | B45: 0.2286 | C45: 0.25 | D45: 0.2237 | E45: -0.2204 | F45: -
A47: Basic Shares Outstanding | B47: 8400 | C47: 8246 | D47: 8400 | E47: 8400 | F47: 8400
A48: EPS (Diluted) | B48: - | C48: 0.06 | D48: 0.05 | E48: 0.04 | F48: 0.05
A49: EPS (Diluted) Growth | B49: 0 | C49: 0.2479 | D49: 0.2252 | E49: -0.2205 | F49: -
A51: Diluted Shares Outstanding | B51: - | C51: 8246 | D51: 8400 | E51: 8400 | F51: 8400
A52: EBITDA | B52: 145 | C52: 105 | D52: 118 | E52: -20 | F52: 98
A54: EBITDA Growth | B54: 0.3828 | C54: -0.1103 | D54: 6.8392 | E54: -1.2072 | F54: -
A56: EBITDA Margin | B56: 0.0127 | C56: - | D56: - | E56: - | F56: -
A57: EBIT | B57: -132 | C57: -142 | D57: - | E57: -230 | F57: -92
A59: Balance Sheet
A60: Assets
A61: Fiscal year is January-December. All values MYR Millions. | B61: 2025 | C61: 2024 | D61: 2023 | E61: 2022 | F61: 2021
A62: Cash & Short Term Investments | B62: 898 | C62: 698 | D62: 138 | E62: 85 | F62: 350
A63: Cash Only | B63: 898 | C63: 498 | D63: 138 | E63: 85 | F63: 29
A64: Cash & Short Term Investments Growth | B64: 0.2861 | C64: 4.0745 | D64: 0.6174 | E64: -0.7571 | F64: -
A66: Cash & ST Investments / Total Assets | B66: 0.2203 | C66: 0.1856 | D66: 0.0485 | E66: 0.0357 | F66: 0.1485
A67: Total Accounts Receivable | B67: 45 | C67: 20 | D67: 44 | E67: 29 | F67: 18
A68: Accounts Receivables, Net | B68: 45 | C68: 15 | D68: 42 | E68: 28 | F68: 17
A69: Accounts Receivables, Gross | B69: 45 | C69: 15 | D69: 42 | E69: 28 | F69: 17
A70: Other Receivables | B70: - | C70: 5 | D70: 2 | E70: 1 | F70: 1
A71: Accounts Receivable Growth | B71: 1.1859 | C71: -0.5358 | D71: 0.5224 | E71: 0.575 | F71: -
A73: Accounts Receivable Turnover | B73: 256.33 | C73: 489.18 | D73: 209.61 | E73: 279.66 | F73: 427.47
A74: Inventories | B74: 1450 | C74: 1339 | D74: 1174 | E74: 1093 | F74: 803
A75: Finished Goods | B75: - | C75: 1339 | D75: 1174 | E75: 1093 | F75: 803
A76: Progress Payments & Other | B76: - | C76: - | D76: - | E76: 0 | F76: -
A77: Other Current Assets | B77: 60 | C77: 49 | D77: 40 | E77: 36 | F77: 43
A78: Prepaid Expenses | B78: - | C78: 4 | D78: 0 | E78: 0 | F78: 0
A79: Miscellaneous Current Assets | B79: 60 | C79: 45 | D79: 40 | E79: 35 | F79: 43
A80: Total Current Assets | B80: 2452 | C80: 2106 | D80: 1396 | E80: 1243 | F80: 1215
A81: Net Property, Plant & Equipment | B81: 1615 | C81: 1442 | D81: 1254 | E81: 1122 | F81: 1131
A82: Property, Plant & Equipment - Gross | B82: - | C82: 1976 | D82: 1720 | E82: 1523 | F82: 1463
A83: Buildings | B83: - | C83: 168 | D83: 164 | E83: 140 | F83: 105
A84: Land & Improvements | B84: - | C84: 97 | D84: 89 | E84: 55 | F84: 50
A85: Construction in Progress | B85: - | C85: 28 | D85: 3 | E85: 6 | F85: 22
A86: Transportation Equipment | B86: - | C86: 64 | D86: 41 | E86: 34 | F86: 30
A87: Other Property, Plant & Equipment | B87: - | C87: 753 | D87: 649 | E87: 553 | F87: 478
A88: Accumulated Depreciation | B88: - | C88: 534 | D88: 466 | E88: 401 | F88: 332
A89: Buildings | B89: - | C89: 21 | D89: 17 | E89: 14 | F89: 12
A90: Transportation Equipment | B90: - | C90: 28 | D90: 29 | E90: 27 | F90: 24
A91: Other Property, Plant & Equipment | B91: - | C91: 485 | D91: 420 | E91: 360 | F91: 297
A92: Intangible Assets | B92: 0 | C92: 0 | D92: 0 | E92: - | F92: 0
A93: Net Other Intangibles | B93: - | C93: 0 | D93: 0 | E93: - | F93: 0
A94: Total Assets | B94: 4076 | C94: 3761 | D94: 2839 | E94: 2380 | F94: 2358
A95: Assets - Total - Growth | B95: 0.0838 | C95: 0.3246 | D95: 0.1927 | E95: 0.0095 | F95: -
A96: Asset Turnover | B96: 2.92 | C96: - | D96: - | E96: - | F96: -
A97: Return On Average Assets | B97: 0.1568 | C97: - | D97: - | E97: - | F97: -
A98: Liabilities & Shareholders' Equity
A99: All values MYR Millions. | B99: 2025 | C99: 2024 | D99: 2023 | E99: 2022 | F99: 2021
A100: ST Debt & Current Portion LT Debt | B100: 196 | C100: 176 | D100: 160 | E100: 141 | F100: 126
A101: Short Term Debt | B101: - | C101: 3 | D101: 5 | E101: 4 | F101: 9
A102: Current Portion of Long Term Debt | B102: 196 | C102: 173 | D102: 155 | E102: 136 | F102: 116
A103: Accounts Payable | B103: 1120 | C103: 936 | D103: 982 | E103: 805 | F103: 640
A104: Accounts Payable Growth | B104: 0.1966 | C104: -0.0466 | D104: 0.2198 | E104: 0.2578 | F104: -
A106: Income Tax Payable | B106: 21 | C106: 25 | D106: 28 | E106: 29 | F106: 30
A107: Other Current Liabilities | B107: 81 | C107: 74 | D107: 222 | E107: 70 | F107: 66
A108: Dividends Payable | B108: - | C108: - | D108: 100 | E108: - | F108: -
A109: Miscellaneous Current Liabilities | B109: 81 | C109: 74 | D109: 122 | E109: 70 | F109: 66
A110: Total Current Liabilities | B110: 1419 | C110: 1212 | D110: 1391 | E110: 1045 | F110: 862
A111: Current Ratio | B111: 1.73 | C111: 1.74 | D111: 1 | E111: 1.19 | F111: 1.41
A112: Quick Ratio | B112: 0.71 | C112: 0.63 | D112: 0.16 | E112: 0.14 | F112: 0.48
A113: Cash Ratio | B113: 0.63 | C113: 0.58 | D113: 0.1 | E113: 0.08 | F113: 0.41
A114: Long-Term Debt | B114: 778 | C114: 712 | D114: 680 | E114: 656 | F114: 716
A115: Long-Term Debt excl. Capitalized Leases | B115: 778 | C115: 712 | D115: 680 | E115: 656 | F115: 716
A116: Non-Convertible Debt | B116: - | C116: - | D116: 47 | E116: 52 | F116: 46
...
